{"RDF": {"Annotation": {"about": "urn:TuftsMorphologyService:adsum:whitakerLat", "creator": {"Agent": {"about": "net.alpheios:tools:wordsxml.v1"}}, "created": {"$": "2019-12-23T06:21:52.514237"}, "rights": {"$": "Short definitions and morphology from Words by William Whitaker, Copyright 1993-2007."}, "hasTarget": {"Description": {"about": "urn:word:adsum"}}, "title": {}, "hasBody": [{"resource": "urn:uuid:idm140440213062536"}, {"resource": "urn:uuid:idm140440213115816"}], "Body": [{"about": "urn:uuid:idm140440213062536", "type": {"resource": "cnt:ContentAsXML"}, "rest": {"entry": {"infl": {"term": {"lang": "lat", "stem": {"$": "ads"}, "suff": {"$": "um"}}, "pofs": {"order": 3, "$": "verb"}, "conj": {"$": "5th"}, "var": {"$": "1st"}, "tense": {"$": "present"}, "voice": {"$": "active"}, "mood": {"$": "indicative"}, "pers": {"$": "1st"}, "num": {"$": "singular"}}, "dict": [{"hdwd": {"lang": "lat", "$": "adsum, adesse, adfui, adfuturus"}, "pofs": {"order": 3, "$": "verb"}, "freq": {"order": 6, "$": "very frequent"}, "src": {"$": "Ox.Lat.Dict."}}, {"hdwd": {"lang": "lat", "$": "adsum, adesse, arfui, arfuturus"}, "pofs": {"order": 3, "$": "verb"}, "age": {"order": 2, "$": "early"}, "freq": {"order": 4, "$": "common"}, "src": {"$": "Lewis+Short"}}], "mean": {"$": "be near, be present, be in attendance, arrive, appear; aid (w/DAT);"}}}}, {"about": "urn:uuid:idm140440213115816", "type": {"resource": "cnt:ContentAsXML"}, "rest": {"entry": {"infl": {"term": {"lang": "lat", "stem": {"$": "adsum"}}, "pofs": {"order": 3, "$": "verb"}, "conj": {"$": "3rd"}, "var": {"$": "1st"}, "tense": {"$": "present"}, "voice": {"$": "active"}, "mood": {"$": "imperative"}, "pers": {"$": "2nd"}, "num": {"$": "singular"}}, "dict": {"hdwd": {"lang": "lat", "$": "adsumo, adsumere, adsumpsi, adsumptus"}, "pofs": {"order": 3, "$": "verb"}, "conj": {"$": "3rd"}, "kind": {"$": "transitive"}, "freq": {"order": 6, "$": "very frequent"}, "src": {"$": "Ox.Lat.Dict."}}, "mean": {"$": "take (to/up/on/from), adopt/raise, use; assume/receive; insert/add; usurp/claim"}}}}]}}}