{"RDF": {"Annotation": {"about": "urn:TuftsMorphologyService:adeo:whitakerLat", "creator": {"Agent": {"about": "net.alpheios:tools:wordsxml.v1"}}, "created": {"$": "2019-12-23T09:19:57.189728"}, "rights": {"$": "Short definitions and morphology from Words by William Whitaker, Copyright 1993-2007."}, "hasTarget": {"Description": {"about": "urn:word:adeo"}}, "title": {}, "hasBody": [{"resource": "urn:uuid:idm140154429843344"}, {"resource": "urn:uuid:idm140154437535136"}], "Body": [{"about": "urn:uuid:idm140154429843344", "type": {"resource": "cnt:ContentAsXML"}, "rest": {"entry": {"infl": {"term": {"lang": "lat", "stem": {"$": "ade"}, "suff": {"$": "o"}}, "pofs": {"order": 3, "$": "verb"}, "conj": {"$": "6th"}, "var": {"$": "1st"}, "tense": {"$": "present"}, "voice": {"$": "active"}, "mood": {"$": "indicative"}, "pers": {"$": "1st"}, "num": {"$": "singular"}}, "dict": {"hdwd": {"lang": "lat", "$": "adeo, adire, adivi(ii), aditus"}, "pofs": {"order": 3, "$": "verb"}, "freq": {"order": 6, "$": "very frequent"}, "src": {"$": "Ox.Lat.Dict."}}, "mean": {"$": "approach; attack; visit, address; undertake; take possession (inheritance);"}}}}, {"about": "urn:uuid:idm140154437535136", "type": {"resource": "cnt:ContentAsXML"}, "rest": {"entry": {"infl": {"term": {"lang": "lat", "stem": {"$": "adeo"}}, "pofs": {"order": 2, "$": "adverb"}, "comp": {"$": "positive"}}, "dict": {"hdwd": {"lang": "lat", "$": "adeo"}, "pofs": {"order": 2, "$": "adverb"}, "freq": {"order": 6, "$": "very frequent"}, "src": {"$": "Ox.Lat.Dict."}}, "mean": {"$": "to such a degree/pass/point; precisely, exactly; thus far; indeed, truly, even;"}}}}]}}}