{"RDF": {"Annotation": {"about": "urn:TuftsMorphologyService:φύλαξ:morpheusgrc", "creator": {"Agent": {"about": "org.perseus:tools:morpheus.v1"}}, "created": {"$": "2020-01-27T06:55:33.378489"}, "rights": {"$": "Morphology provided by Morpheus from the Perseus Digital Library at Tufts University."}, "hasTarget": {"Description": {"about": "urn:word:φύλαξ"}}, "title": {}, "hasBody": {"resource": "urn:uuid:idm140090967341832"}, "Body": {"about": "urn:uuid:idm140090967341832", "type": {"resource": "cnt:ContentAsXML"}, "rest": {"entry": {"uri": null, "dict": {"hdwd": {"lang": "grc", "$": "φύλαξ"}, "pofs": {"order": 3, "$": "noun"}, "decl": {"$": "3rd"}, "gend": {"$": "masculine"}}, "infl": [{"term": {"lang": "grc", "stem": {"$": "φυλα"}, "suff": {"$": "ξ"}}, "pofs": {"order": 3, "$": "noun"}, "decl": {"$": "3rd"}, "case": {"order": 7, "$": "nominative"}, "gend": {"$": "masculine"}, "num": {"$": "singular"}, "stemtype": {"$": "c_kos"}}, {"term": {"lang": "grc", "stem": {"$": "φυλα"}, "suff": {"$": "ξ"}}, "pofs": {"order": 3, "$": "noun"}, "decl": {"$": "3rd"}, "case": {"order": 1, "$": "vocative"}, "gend": {"$": "masculine"}, "num": {"$": "singular"}, "stemtype": {"$": "c_kos"}}]}}}}}}