{"RDF": {"Annotation": {"about": "urn:TuftsMorphologyService:ἄστει:morpheusgrc", "creator": {"Agent": {"about": "org.perseus:tools:morpheus.v1"}}, "created": {"$": "2020-01-28T09:44:23.703343"}, "rights": {"$": "Morphology provided by Morpheus from the Perseus Digital Library at Tufts University."}, "hasTarget": {"Description": {"about": "urn:word:ἄστει"}}, "title": {}, "hasBody": {"resource": "urn:uuid:idm140090968452712"}, "Body": {"about": "urn:uuid:idm140090968452712", "type": {"resource": "cnt:ContentAsXML"}, "rest": {"entry": {"uri": null, "dict": {"hdwd": {"lang": "grc", "$": "ἄστυ"}, "pofs": {"order": 3, "$": "noun"}, "decl": {"$": "3rd"}, "gend": {"$": "neuter"}}, "infl": [{"term": {"lang": "grc", "stem": {"$": "ἀστ"}, "suff": {"$": "ει"}}, "pofs": {"order": 3, "$": "noun"}, "decl": {"$": "3rd"}, "case": {"order": 7, "$": "nominative"}, "gend": {"$": "neuter"}, "num": {"$": "dual"}, "dial": {"$": "Attic epic"}, "stemtype": {"$": "us_ews"}, "morph": {"$": "contr"}}, {"term": {"lang": "grc", "stem": {"$": "ἀστ"}, "suff": {"$": "ει"}}, "pofs": {"order": 3, "$": "noun"}, "decl": {"$": "3rd"}, "case": {"order": 1, "$": "vocative"}, "gend": {"$": "neuter"}, "num": {"$": "dual"}, "dial": {"$": "Attic epic"}, "stemtype": {"$": "us_ews"}, "morph": {"$": "contr"}}, {"term": {"lang": "grc", "stem": {"$": "ἀστ"}, "suff": {"$": "ει"}}, "pofs": {"order": 3, "$": "noun"}, "decl": {"$": "3rd"}, "case": {"order": 4, "$": "accusative"}, "gend": {"$": "neuter"}, "num": {"$": "dual"}, "dial": {"$": "Attic epic"}, "stemtype": {"$": "us_ews"}, "morph": {"$": "contr"}}, {"term": {"lang": "grc", "stem": {"$": "ἀστ"}, "suff": {"$": "ει"}}, "pofs": {"order": 3, "$": "noun"}, "decl": {"$": "3rd"}, "case": {"order": 5, "$": "dative"}, "gend": {"$": "neuter"}, "num": {"$": "singular"}, "stemtype": {"$": "us_ews"}, "morph": {"$": "contr"}}]}}}}}}